fssucatools2/__init__.py
fssucatools2/fssucatools2.py
fssucatools2-0.1.0.dist-info/licenses/LICENSE
fssucatools2-0.1.0.dist-info/METADATA
fssucatools2-0.1.0.dist-info/WHEEL
fssucatools2-0.1.0.dist-info/top_level.txt
fssucatools2-0.1.0.dist-info/RECORD
